abx_spec_config/__init__.py
abx_spec_config/base_configset.py
abx_spec_config/toml_util.py
abx_spec_config-0.1.0.dist-info/METADATA
abx_spec_config-0.1.0.dist-info/WHEEL
abx_spec_config-0.1.0.dist-info/entry_points.txt
abx_spec_config-0.1.0.dist-info/RECORD
