Metadata-Version: 2.4
Name: abx-spec-config
Version: 0.1.0
Summary: The common shared interfaces for the ABX ArchiveBox plugin ecosystem.
Requires-Python: >=3.10
Requires-Dist: abx>=0.1.0
Requires-Dist: pydantic-settings>=2.6.0
Requires-Dist: pydantic>=2.9.2
Requires-Dist: python-benedict>=0.34.0
Requires-Dist: rich>=13.9.3
